fast_binance/__init__.py
fast_binance/archieve_files.py
fast_binance/offline_fetcher.py
fast_binance/online_fetcher.py
fast_binance/utils.py
fast_binance-1.1.2.dist-info/LICENSE
fast_binance-1.1.2.dist-info/METADATA
fast_binance-1.1.2.dist-info/WHEEL
fast_binance-1.1.2.dist-info/top_level.txt
fast_binance-1.1.2.dist-info/RECORD
