Metadata-Version: 2.1
Name: fast-binance
Version: 1.1.2
Summary: Asyncful wrapper around python-binance module and data.binance.vision .
Home-page: https://github.com/mkaanerkoc/fast-binance
Author: Kaan Erkoc
Author-email: mkaanerkoc@gmail.com
License: MIT
Keywords: binance exchange rest api bitcoin ethereum btc eth neo
Classifier: Intended Audience :: Developers
Classifier: License :: OSI Approved :: MIT License
Classifier: Operating System :: OS Independent
Classifier: Programming Language :: Python :: 3
Classifier: Programming Language :: Python :: 3.5
Classifier: Programming Language :: Python :: 3.6
Classifier: Programming Language :: Python :: 3.7
Classifier: Programming Language :: Python
Classifier: Topic :: Software Development :: Libraries :: Python Modules
License-File: LICENSE
Requires-Dist: pandas
Requires-Dist: python-binance
